tenantpy/__init__.py
tenantpy/settings.py
tenantpy/backend/__init__.py
tenantpy/backend/cache.py
tenantpy/backend/context.py
tenantpy/backend/mysql.py
tenantpy/contrib/__init__.py
tenantpy/contrib/flask.py
tenantpy/logging/__init__.py
tenantpy/logging/base.py
tenantpy/sample/__init__.py
tenantpy/sample/jaeger.py
tenantpy/sample/trace_malloc.py
tenantpy/utils/__init__.py
tenantpy/utils/lru.py
tenantpy/utils/proxy.py
tests/backend/__init__.py
tests/backend/mysql.py
tests/logging/__init__.py
tests/logging/base.py
tests/tenantpy/__init__.py
tests/tenantpy/backend/__init__.py
tests/tenantpy/backend/mysql.py
tests/tenantpy/logging/__init__.py
tests/tenantpy/logging/base.py
tests/tenantpy/utils/__init__.py
tests/tenantpy/utils/lru.py
tests/utils/__init__.py
tests/utils/lru.py
tenantpy-1.0.5.dist-info/METADATA
tenantpy-1.0.5.dist-info/WHEEL
tenantpy-1.0.5.dist-info/top_level.txt
tenantpy-1.0.5.dist-info/RECORD
