Metadata-Version: 2.1
Name: tenantpy
Version: 1.0.5
Summary: Tenant Management For Web Application
Home-page: UNKNOWN
Author: zhouhao
Author-email: zhouhao19931002@hotmail.com
Maintainer: zhouhao
License: UNKNOWN
Platform: UNKNOWN
Classifier: Programming Language :: Python :: 3.7
Requires-Python: >=3.7.0
Requires-Dist: dbutils (>=1.3)
Requires-Dist: peewee (>=3.9.3)
Requires-Dist: pymysql (==0.9.2)
Requires-Dist: pympler (==0.9)
Requires-Dist: redis (==3.2.1)
Requires-Dist: flask (==1.0.2)
Requires-Dist: jaeger-client (==4.3.0)
